fhailib/__init__.py
fhailib/RT_DETR_util/RT_DETR_Tool.py
fhailib/RT_DETR_util/src/core/__init__.py
fhailib/RT_DETR_util/src/core/config.py
fhailib/RT_DETR_util/src/core/yaml_config.py
fhailib/RT_DETR_util/src/core/yaml_utils.py
fhailib/RT_DETR_util/src/data/__init__.py
fhailib/RT_DETR_util/src/data/dataloader.py
fhailib/RT_DETR_util/src/data/functional.py
fhailib/RT_DETR_util/src/data/transforms.py
fhailib/RT_DETR_util/src/data/coco/__init__.py
fhailib/RT_DETR_util/src/data/coco/coco_dataset.py
fhailib/RT_DETR_util/src/data/coco/coco_eval.py
fhailib/RT_DETR_util/src/data/coco/coco_utils.py
fhailib/RT_DETR_util/src/misc/__init__.py
fhailib/RT_DETR_util/src/misc/dist.py
fhailib/RT_DETR_util/src/misc/logger.py
fhailib/RT_DETR_util/src/misc/visualizer.py
fhailib/RT_DETR_util/src/nn/arch/__init__.py
fhailib/RT_DETR_util/src/nn/arch/classification.py
fhailib/RT_DETR_util/src/nn/backbone/__init__.py
fhailib/RT_DETR_util/src/nn/backbone/common.py
fhailib/RT_DETR_util/src/nn/backbone/presnet.py
fhailib/RT_DETR_util/src/nn/backbone/test_resnet.py
fhailib/RT_DETR_util/src/nn/backbone/utils.py
fhailib/RT_DETR_util/src/nn/criterion/__init__.py
fhailib/RT_DETR_util/src/nn/criterion/utils.py
fhailib/RT_DETR_util/src/optim/__init__.py
fhailib/RT_DETR_util/src/optim/amp.py
fhailib/RT_DETR_util/src/optim/ema.py
fhailib/RT_DETR_util/src/optim/optim.py
fhailib/RT_DETR_util/src/solver/__init__.py
fhailib/RT_DETR_util/src/solver/det_engine.py
fhailib/RT_DETR_util/src/solver/det_solver.py
fhailib/RT_DETR_util/src/solver/solver.py
fhailib/RT_DETR_util/src/zoo/rtdetr/__init__.py
fhailib/RT_DETR_util/src/zoo/rtdetr/box_ops.py
fhailib/RT_DETR_util/src/zoo/rtdetr/denoising.py
fhailib/RT_DETR_util/src/zoo/rtdetr/hybrid_encoder.py
fhailib/RT_DETR_util/src/zoo/rtdetr/matcher.py
fhailib/RT_DETR_util/src/zoo/rtdetr/rtdetr.py
fhailib/RT_DETR_util/src/zoo/rtdetr/rtdetr_criterion.py
fhailib/RT_DETR_util/src/zoo/rtdetr/rtdetr_decoder.py
fhailib/RT_DETR_util/src/zoo/rtdetr/rtdetr_postprocessor.py
fhailib-1.0.10.dist-info/METADATA
fhailib-1.0.10.dist-info/WHEEL
fhailib-1.0.10.dist-info/top_level.txt
fhailib-1.0.10.dist-info/RECORD
